Workbook

Sheet Como usar
A1: Planilha de Precificação e Encomendas · Natal 3D
A2: Funciona no Excel e no Google Planilhas (Arquivo → Importar).
A4: COMO USAR
A5: 1. Aba Calculadora: preencha as células AMARELAS da configuração (preço do rolo, custo da hora etc.) uma vez só.
A6: 2. Em cada linha da Calculadora, coloque o nome da peça, o peso em gramas e o tempo de impressão que o fatiador mostrar. O custo e o preço sugerido aparecem sozinhos.
A7: 3. Aba Encomendas: uma linha por pedido. Escreva a peça com o MESMO nome da Calculadora para o lucro ser calculado automaticamente.
A8: 4. Marque "Sim" em Pago e Entregue conforme o pedido avança. As linhas não pagas ficam em vermelho.
A9: 5. Aba Estoque: anote a meta de peças prontas e quantas já fez e vendeu.
A10: 6. Aba Resumo: faturamento, quanto já recebeu, quanto falta receber e o lucro estimado, tudo automático.
A12: LEGENDA
A13: Células amarelas = você preenche. Células brancas = fórmulas (não precisa mexer).
A14: As primeiras linhas trazem exemplos. Pode apagar e escrever os seus.
A16: Valores de custo da hora (R$ 0,50) e reserva para falhas (10%) são médias sugeridas para impressoras domésticas. Ajuste para a sua realidade.

Sheet Resumo
A1: Resumo das vendas
A2: Tudo automático, a partir da aba Encomendas.
A4: Pedidos registrados | B4: =COUNTA(Encomendas!B5:B304) -> 1
A5: Peças vendidas | B5: =SUM(Encomendas!G5:G304) -> 3
A6: Faturamento total | B6: =SUM(Encomendas!I5:I304) -> 36
A7: Já recebido | B7: =SUMIFS(Encomendas!I5:I304,Encomendas!K5:K304,"Sim") -> 36
A8: Falta receber | B8: =B6-B7 -> 0
A9: Lucro estimado | B9: =SUM(Encomendas!N5:N304) -> 26.895
A10: Ticket médio por pedido | B10: =IF(B4=0,0,B6/B4) -> 36
A11: Pedidos ainda não entregues | B11: =COUNTIFS(Encomendas!B5:B304,"<>",Encomendas!L5:L304,"<>Sim") -> 1
A12: Peças em estoque (pronta entrega) | B12: =SUM(Estoque!F5:F64) -> 5

Sheet Calculadora
A1: Calculadora de custo e preço
A2: Preencha a configuração (amarelo) e depois cada peça.
A4: Preço do rolo de 1 kg (R$) | B4: 100
A5: Custo da hora de impressora (R$/h) | B5: 0.5
A6: Reserva para falhas (%) | B6: 0.1
A7: Lucro desejado (%) | B7: 2
A8: Taxa da plataforma (%) · Shopee ≈ 20%, venda direta = 0 | B8: 0
A10: Peça | B10: Peso (g) | C10: Tempo de impressão (h) | D10: Embalagem (R$) | E10: Filamento (R$) | F10: Máquina e energia (R$) | G10: Reserva falhas (R$) | H10: Custo total (R$) | I10: Preço sugerido (R$) | J10: Lucro por peça (R$)
A11: Enfeite com nome | B11: 15 | C11: 0.7 | D11: 1 | E11: =IF(B11="","",B11*$B$4/1000) -> 1.5 | F11: =IF(B11="","",C11*$B$5) -> 0.35 | G11: =IF(B11="","",(E11+F11)*$B$6) -> 0.185 | H11: =IF(B11="","",E11+F11+G11+D11) -> 3.035 | I11: =IF(B11="","",IF($B$8>=1,H11*(1+$B$7),H11*(1+$B$7)/(1-$B$8))) -> 9.105 | J11: =IF(B11="","",I11-H11-I11*$B$8) -> 6.07
A12: Árvore espiral 15 cm | B12: 45 | C12: 2.5 | D12: 1.5 | E12: =IF(B12="","",B12*$B$4/1000) -> 4.5 | F12: =IF(B12="","",C12*$B$5) -> 1.25 | G12: =IF(B12="","",(E12+F12)*$B$6) -> 0.575 | H12: =IF(B12="","",E12+F12+G12+D12) -> 7.825 | I12: =IF(B12="","",IF($B$8>=1,H12*(1+$B$7),H12*(1+$B$7)/(1-$B$8))) -> 23.475 | J12: =IF(B12="","",I12-H12-I12*$B$8) -> 15.65
A13: Rena de tricô | B13: 60 | C13: 3 | D13: 2 | E13: =IF(B13="","",B13*$B$4/1000) -> 6 | F13: =IF(B13="","",C13*$B$5) -> 1.5 | G13: =IF(B13="","",(E13+F13)*$B$6) -> 0.75 | H13: =IF(B13="","",E13+F13+G13+D13) -> 10.25 | I13: =IF(B13="","",IF($B$8>=1,H13*(1+$B$7),H13*(1+$B$7)/(1-$B$8))) -> 30.75 | J13: =IF(B13="","",I13-H13-I13*$B$8) -> 20.5
A14: Cortador de biscoito (kit 6) | B14: 40 | C14: 1.5 | D14: 1.5 | E14: =IF(B14="","",B14*$B$4/1000) -> 4 | F14: =IF(B14="","",C14*$B$5) -> 0.75 | G14: =IF(B14="","",(E14+F14)*$B$6) -> 0.475 | H14: =IF(B14="","",E14+F14+G14+D14) -> 6.725 | I14: =IF(B14="","",IF($B$8>=1,H14*(1+$B$7),H14*(1+$B$7)/(1-$B$8))) -> 20.175 | J14: =IF(B14="","",I14-H14-I14*$B$8) -> 13.45
E15: =IF(B15="","",B15*$B$4/1000) | F15: =IF(B15="","",C15*$B$5) | G15: =IF(B15="","",(E15+F15)*$B$6) | H15: =IF(B15="","",E15+F15+G15+D15) | I15: =IF(B15="","",IF($B$8>=1,H15*(1+$B$7),H15*(1+$B$7)/(1-$B$8))) | J15: =IF(B15="","",I15-H15-I15*$B$8)
E16: =IF(B16="","",B16*$B$4/1000) | F16: =IF(B16="","",C16*$B$5) | G16: =IF(B16="","",(E16+F16)*$B$6) | H16: =IF(B16="","",E16+F16+G16+D16) | I16: =IF(B16="","",IF($B$8>=1,H16*(1+$B$7),H16*(1+$B$7)/(1-$B$8))) | J16: =IF(B16="","",I16-H16-I16*$B$8)
E17: =IF(B17="","",B17*$B$4/1000) | F17: =IF(B17="","",C17*$B$5) | G17: =IF(B17="","",(E17+F17)*$B$6) | H17: =IF(B17="","",E17+F17+G17+D17) | I17: =IF(B17="","",IF($B$8>=1,H17*(1+$B$7),H17*(1+$B$7)/(1-$B$8))) | J17: =IF(B17="","",I17-H17-I17*$B$8)
E18: =IF(B18="","",B18*$B$4/1000) | F18: =IF(B18="","",C18*$B$5) | G18: =IF(B18="","",(E18+F18)*$B$6) | H18: =IF(B18="","",E18+F18+G18+D18) | I18: =IF(B18="","",IF($B$8>=1,H18*(1+$B$7),H18*(1+$B$7)/(1-$B$8))) | J18: =IF(B18="","",I18-H18-I18*$B$8)
E19: =IF(B19="","",B19*$B$4/1000) | F19: =IF(B19="","",C19*$B$5) | G19: =IF(B19="","",(E19+F19)*$B$6) | H19: =IF(B19="","",E19+F19+G19+D19) | I19: =IF(B19="","",IF($B$8>=1,H19*(1+$B$7),H19*(1+$B$7)/(1-$B$8))) | J19: =IF(B19="","",I19-H19-I19*$B$8)
E20: =IF(B20="","",B20*$B$4/1000) | F20: =IF(B20="","",C20*$B$5) | G20: =IF(B20="","",(E20+F20)*$B$6) | H20: =IF(B20="","",E20+F20+G20+D20) | I20: =IF(B20="","",IF($B$8>=1,H20*(1+$B$7),H20*(1+$B$7)/(1-$B$8))) | J20: =IF(B20="","",I20-H20-I20*$B$8)
E21: =IF(B21="","",B21*$B$4/1000) | F21: =IF(B21="","",C21*$B$5) | G21: =IF(B21="","",(E21+F21)*$B$6) | H21: =IF(B21="","",E21+F21+G21+D21) | I21: =IF(B21="","",IF($B$8>=1,H21*(1+$B$7),H21*(1+$B$7)/(1-$B$8))) | J21: =IF(B21="","",I21-H21-I21*$B$8)
E22: =IF(B22="","",B22*$B$4/1000) | F22: =IF(B22="","",C22*$B$5) | G22: =IF(B22="","",(E22+F22)*$B$6) | H22: =IF(B22="","",E22+F22+G22+D22) | I22: =IF(B22="","",IF($B$8>=1,H22*(1+$B$7),H22*(1+$B$7)/(1-$B$8))) | J22: =IF(B22="","",I22-H22-I22*$B$8)
E23: =IF(B23="","",B23*$B$4/1000) | F23: =IF(B23="","",C23*$B$5) | G23: =IF(B23="","",(E23+F23)*$B$6) | H23: =IF(B23="","",E23+F23+G23+D23) | I23: =IF(B23="","",IF($B$8>=1,H23*(1+$B$7),H23*(1+$B$7)/(1-$B$8))) | J23: =IF(B23="","",I23-H23-I23*$B$8)
E24: =IF(B24="","",B24*$B$4/1000) | F24: =IF(B24="","",C24*$B$5) | G24: =IF(B24="","",(E24+F24)*$B$6) | H24: =IF(B24="","",E24+F24+G24+D24) | I24: =IF(B24="","",IF($B$8>=1,H24*(1+$B$7),H24*(1+$B$7)/(1-$B$8))) | J24: =IF(B24="","",I24-H24-I24*$B$8)
E25: =IF(B25="","",B25*$B$4/1000) | F25: =IF(B25="","",C25*$B$5) | G25: =IF(B25="","",(E25+F25)*$B$6) | H25: =IF(B25="","",E25+F25+G25+D25) | I25: =IF(B25="","",IF($B$8>=1,H25*(1+$B$7),H25*(1+$B$7)/(1-$B$8))) | J25: =IF(B25="","",I25-H25-I25*$B$8)
E26: =IF(B26="","",B26*$B$4/1000) | F26: =IF(B26="","",C26*$B$5) | G26: =IF(B26="","",(E26+F26)*$B$6) | H26: =IF(B26="","",E26+F26+G26+D26) | I26: =IF(B26="","",IF($B$8>=1,H26*(1+$B$7),H26*(1+$B$7)/(1-$B$8))) | J26: =IF(B26="","",I26-H26-I26*$B$8)
... E50: =IF(B50="","",B50*$B$4/1000) | F50: =IF(B50="","",C50*$B$5) | G50: =IF(B50="","",(E50+F50)*$B$6) | H50: =IF(B50="","",E50+F50+G50+D50) | I50: =IF(B50="","",IF($B$8>=1,H50*(1+$B$7),H50*(1+$B$7)/(1-$B$8))) | J50: =IF(B50="","",I50-H50-I50*$B$8)
A52: Preço sugerido = custo total × (1 + lucro desejado), dividido por (1 − taxa da plataforma). Arredonde para um preço "bonito" (ex.: R$ 9,90).

Sheet Encomendas
A1: Controle de encomendas
A2: Uma linha por pedido. Escreva a peça igual ao nome da Calculadora.
A4: Data | B4: Cliente | C4: WhatsApp | D4: Peça | E4: Personalização (nome) | F4: Cor | G4: Qtd | H4: Preço unit. (R$) | I4: Total (R$) | J4: Entregar até | K4: Pago? | L4: Entregue? | M4: Custo unit. (R$) | N4: Lucro (R$)
A5: 46331 | B5: Maria Souza | C5: (79) 99999-0000 | D5: Enfeite com nome | E5: Ana, Pedro, Lia | F5: Branco/vermelho | G5: 3 | H5: 12 | I5: =IF(G5="","",G5*H5) -> 36 | J5: 46338 | K5: Sim | L5: Não | M5: =IF(D5="","",IFERROR(INDEX(Calculadora!$H$11:$H$50,MATCH(D5,Calculadora!$A$11:$A$50,0)),"")) -> 3.035 | N5: =IF(OR(I5="",M5=""),"",I5-G5*M5) -> 26.895
I6: =IF(G6="","",G6*H6) | M6: =IF(D6="","",IFERROR(INDEX(Calculadora!$H$11:$H$50,MATCH(D6,Calculadora!$A$11:$A$50,0)),"")) | N6: =IF(OR(I6="",M6=""),"",I6-G6*M6)
I7: =IF(G7="","",G7*H7) | M7: =IF(D7="","",IFERROR(INDEX(Calculadora!$H$11:$H$50,MATCH(D7,Calculadora!$A$11:$A$50,0)),"")) | N7: =IF(OR(I7="",M7=""),"",I7-G7*M7)
I8: =IF(G8="","",G8*H8) | M8: =IF(D8="","",IFERROR(INDEX(Calculadora!$H$11:$H$50,MATCH(D8,Calculadora!$A$11:$A$50,0)),"")) | N8: =IF(OR(I8="",M8=""),"",I8-G8*M8)
I9: =IF(G9="","",G9*H9) | M9: =IF(D9="","",IFERROR(INDEX(Calculadora!$H$11:$H$50,MATCH(D9,Calculadora!$A$11:$A$50,0)),"")) | N9: =IF(OR(I9="",M9=""),"",I9-G9*M9)
I10: =IF(G10="","",G10*H10) | M10: =IF(D10="","",IFERROR(INDEX(Calculadora!$H$11:$H$50,MATCH(D10,Calculadora!$A$11:$A$50,0)),"")) | N10: =IF(OR(I10="",M10=""),"",I10-G10*M10)
I11: =IF(G11="","",G11*H11) | M11: =IF(D11="","",IFERROR(INDEX(Calculadora!$H$11:$H$50,MATCH(D11,Calculadora!$A$11:$A$50,0)),"")) | N11: =IF(OR(I11="",M11=""),"",I11-G11*M11)
I12: =IF(G12="","",G12*H12) | M12: =IF(D12="","",IFERROR(INDEX(Calculadora!$H$11:$H$50,MATCH(D12,Calculadora!$A$11:$A$50,0)),"")) | N12: =IF(OR(I12="",M12=""),"",I12-G12*M12)
I13: =IF(G13="","",G13*H13) | M13: =IF(D13="","",IFERROR(INDEX(Calculadora!$H$11:$H$50,MATCH(D13,Calculadora!$A$11:$A$50,0)),"")) | N13: =IF(OR(I13="",M13=""),"",I13-G13*M13)
I14: =IF(G14="","",G14*H14) | M14: =IF(D14="","",IFERROR(INDEX(Calculadora!$H$11:$H$50,MATCH(D14,Calculadora!$A$11:$A$50,0)),"")) | N14: =IF(OR(I14="",M14=""),"",I14-G14*M14)
I15: =IF(G15="","",G15*H15) | M15: =IF(D15="","",IFERROR(INDEX(Calculadora!$H$11:$H$50,MATCH(D15,Calculadora!$A$11:$A$50,0)),"")) | N15: =IF(OR(I15="",M15=""),"",I15-G15*M15)
I16: =IF(G16="","",G16*H16) | M16: =IF(D16="","",IFERROR(INDEX(Calculadora!$H$11:$H$50,MATCH(D16,Calculadora!$A$11:$A$50,0)),"")) | N16: =IF(OR(I16="",M16=""),"",I16-G16*M16)
I17: =IF(G17="","",G17*H17) | M17: =IF(D17="","",IFERROR(INDEX(Calculadora!$H$11:$H$50,MATCH(D17,Calculadora!$A$11:$A$50,0)),"")) | N17: =IF(OR(I17="",M17=""),"",I17-G17*M17)
... I304: =IF(G304="","",G304*H304) | M304: =IF(D304="","",IFERROR(INDEX(Calculadora!$H$11:$H$50,MATCH(D304,Calculadora!$A$11:$A$50,0)),"")) | N304: =IF(OR(I304="",M304=""),"",I304-G304*M304)

Sheet Estoque
A1: Estoque de pronta entrega
A2: Peças sem nome que você deixa prontas para vender na hora.
A4: Peça | B4: Cor | C4: Meta | D4: Feitas | E4: Vendidas | F4: Em estoque | G4: Falta produzir
A5: Árvore espiral 15 cm | B5: Verde | C5: 20 | D5: 8 | E5: 3 | F5: =IF(A5="","",D5-E5) -> 5 | G5: =IF(A5="","",MAX(0,C5-D5)) -> 12
F6: =IF(A6="","",D6-E6) | G6: =IF(A6="","",MAX(0,C6-D6))
F7: =IF(A7="","",D7-E7) | G7: =IF(A7="","",MAX(0,C7-D7))
F8: =IF(A8="","",D8-E8) | G8: =IF(A8="","",MAX(0,C8-D8))
F9: =IF(A9="","",D9-E9) | G9: =IF(A9="","",MAX(0,C9-D9))
F10: =IF(A10="","",D10-E10) | G10: =IF(A10="","",MAX(0,C10-D10))
F11: =IF(A11="","",D11-E11) | G11: =IF(A11="","",MAX(0,C11-D11))
F12: =IF(A12="","",D12-E12) | G12: =IF(A12="","",MAX(0,C12-D12))
F13: =IF(A13="","",D13-E13) | G13: =IF(A13="","",MAX(0,C13-D13))
F14: =IF(A14="","",D14-E14) | G14: =IF(A14="","",MAX(0,C14-D14))
F15: =IF(A15="","",D15-E15) | G15: =IF(A15="","",MAX(0,C15-D15))
F16: =IF(A16="","",D16-E16) | G16: =IF(A16="","",MAX(0,C16-D16))
F17: =IF(A17="","",D17-E17) | G17: =IF(A17="","",MAX(0,C17-D17))
... F64: =IF(A64="","",D64-E64) | G64: =IF(A64="","",MAX(0,C64-D64))
